FMXL/__init__.py
FMXL/fmxl.py
fmxl-0.1.1.dist-info/LICENSE.txt
fmxl-0.1.1.dist-info/METADATA
fmxl-0.1.1.dist-info/WHEEL
fmxl-0.1.1.dist-info/top_level.txt
fmxl-0.1.1.dist-info/RECORD
